{
  "gitSyncId": "6623c49634ed1c2c6d4c255c_5be20ef3-9acc-4de7-9897-5ee08c23c5e9",
  "id": "Withdraw_rejectWithdraw",
  "pluginId": "restapi-plugin",
  "pluginType": "API",
  "unpublishedAction": {
    "actionConfiguration": {
      "autoGeneratedHeaders": [
        {
          "key": "content-type",
          "value": "application/json"
        }
      ],
      "body": "",
      "bodyFormData": [],
      "encodeParamsToggle": true,
      "formData": {
        "apiContentType": "none"
      },
      "headers": [
        {
          "key": "Authorization",
          "value": "Bearer {{appsmith.store.token}}"
        }
      ],
      "httpMethod": "PUT",
      "httpVersion": "HTTP11",
      "paginationType": "NONE",
      "path": "/admin/withdrawals/{{tbl_withdraws.selectedRow.id}}/reject",
      "pluginSpecifiedTemplates": [
        {
          "value": true
        }
      ],
      "queryParameters": [],
      "timeoutInMillisecond": 10000
    },
    "confirmBeforeExecute": false,
    "datasource": {
      "id": "Livestream BE",
      "isAutoGenerated": false,
      "name": "Livestream BE",
      "pluginId": "restapi-plugin"
    },
    "dynamicBindingPathList": [
      {
        "key": "path"
      },
      {
        "key": "headers[0].value"
      }
    ],
    "executeOnLoad": false,
    "name": "rejectWithdraw",
    "pageId": "Withdraw",
    "userSetOnLoad": false
  }
}